swimrankingsscraper/__init__.py
swimrankingsscraper/swimrankingsscraper.py
swimrankingsscraper-0.1.4.dist-info/LICENSE
swimrankingsscraper-0.1.4.dist-info/METADATA
swimrankingsscraper-0.1.4.dist-info/WHEEL
swimrankingsscraper-0.1.4.dist-info/top_level.txt
swimrankingsscraper-0.1.4.dist-info/RECORD
