Metadata-Version: 2.1
Name: swimrankingsscraper
Version: 0.1.4
Summary: A scraper for swimrankings.net
Home-page: https://swimrankingsscraper.readthedocs.io/
Author: Bas Neeleman
Author-email: bas@neeleman-mail.nl
License: MIT
Classifier: Development Status :: 3 - Alpha
Classifier: Intended Audience :: Developers
Classifier: License :: OSI Approved :: MIT License
Classifier: Programming Language :: Python :: 3.10
License-File: LICENSE
Requires-Dist: requests
Requires-Dist: beautifulsoup4
Requires-Dist: lxml
